tabm.py
tabm-0.0.3.dist-info/licenses/LICENSE
tabm-0.0.3.dist-info/WHEEL
tabm-0.0.3.dist-info/METADATA
tabm-0.0.3.dist-info/RECORD
